setup.py
RAYLEIGH.egg-info/PKG-INFO
RAYLEIGH.egg-info/SOURCES.txt
RAYLEIGH.egg-info/dependency_links.txt
RAYLEIGH.egg-info/entry_points.txt
RAYLEIGH.egg-info/pbr.json
RAYLEIGH.egg-info/requires.txt
RAYLEIGH.egg-info/top_level.txt
analysis/__init__.py
analysis/dsc_parser.py
analysis/frame_parser.py
analysis/plotter.py
analysis/rayleigh.py