Metadata-Version: 1.1
Name: RAYLEIGH
Version: 0.2.0
Summary: A basic plotter and converter for output files from TimePix chips.
Home-page: https://www.github.com/GuiltyDolphin/RAYLEIGH
Author: GuiltyDolphin
Author-email: GuiltyDolphin@gmail.com
License: GPLv3
Download-URL: https://github.com/GuiltyDolphin/RAYLEIGH/tarball/0.2.0
Keywords: plotter ray rayleigh json converter
Platform: UNKNOWN
Classifier: Programming Language :: Python
Classifier: Programming Language :: Python :: 3
Classifier: License :: OSI Approved :: GNU General Public License v3 (GPLv3)
Classifier: Operating System :: POSIX :: Linux
